yourlog/__init__.py
yourlog/__init__.pyi
yourlog-1.2.0.dist-info/LICENSE
yourlog-1.2.0.dist-info/METADATA
yourlog-1.2.0.dist-info/WHEEL
yourlog-1.2.0.dist-info/top_level.txt
yourlog-1.2.0.dist-info/RECORD
