Metadata-Version: 2.1
Name: yourlog
Version: 1.2.0
Summary: Simple python logger
Author: Kiber
License: Apache License
Project-URL: Homepage, https://github.com/Kiber2009/yourlog
Project-URL: Documentation, https://github.com/Kiber2009/yourlog/wiki
Project-URL: Repository, https://github.com/Kiber2009/yourlog.git
Project-URL: Issues, https://github.com/Kiber2009/yourlog/issues
Project-URL: Changelog, https://github.com/Kiber2009/yourlog/blob/master/CHANGELOG.md
Classifier: Programming Language :: Python :: 3
Classifier: License :: OSI Approved :: Apache Software License
Classifier: Operating System :: OS Independent
Classifier: Development Status :: 5 - Production/Stable
Requires-Python: >=3.8
License-File: LICENSE
